escodesearcher/__init__.py
escodesearcher/bingsearch.py
escodesearcher/fetch_code.py
escodesearcher/search_code.py
escodesearcher/urls_fetcher.py
escodesearcher/assets/__init__.py
escodesearcher/assets/site_functions.py
escodesearcher-0.0.5.dist-info/LICENSE
escodesearcher-0.0.5.dist-info/METADATA
escodesearcher-0.0.5.dist-info/WHEEL
escodesearcher-0.0.5.dist-info/top_level.txt
escodesearcher-0.0.5.dist-info/RECORD
