Metadata-Version: 2.1
Name: escodesearcher
Version: 0.0.5
Summary: A source code searcher
Home-page: UNKNOWN
Author: Mohamed Ashraf
Author-email: Mohamed.ashraf881999@gmail.com
License: UNKNOWN
Project-URL: Bug Tracker, https://github.com/xTrimy/escodesearcher/issues
Project-URL: Documentation, https://github.com/xTrimy/escodesearcher/blob/master/README.md
Project-URL: Source Code, https://github.com/xTrimy/escodesearcher/
Platform: UNKNOWN
Classifier: Programming Language :: Python :: 3
Classifier: License :: OSI Approved :: MIT License
Classifier: Operating System :: OS Independent
Requires-Python: >=3.6
